dynamixel_easy_sdk/__init__.py
dynamixel_easy_sdk/connector.py
dynamixel_easy_sdk/control_table.py
dynamixel_easy_sdk/data_types.py
dynamixel_easy_sdk/dynamixel_error.py
dynamixel_easy_sdk/group_executor.py
dynamixel_easy_sdk/motor.py
dynamixel_easy_sdk/control_table/2xc430_w250.model
dynamixel_easy_sdk/control_table/2xl430_w250.model
dynamixel_easy_sdk/control_table/dynamixel.model
dynamixel_easy_sdk/control_table/h42_20_s300_ra.model
dynamixel_easy_sdk/control_table/h54_100_s500_ra.model
dynamixel_easy_sdk/control_table/h54_200_s500_ra.model
dynamixel_easy_sdk/control_table/m42_10_s260_ra.model
dynamixel_easy_sdk/control_table/m54_40_s250_ra.model
dynamixel_easy_sdk/control_table/m54_60_s250_ra.model
dynamixel_easy_sdk/control_table/mx_106.model
dynamixel_easy_sdk/control_table/mx_28.model
dynamixel_easy_sdk/control_table/mx_64.model
dynamixel_easy_sdk/control_table/ph42_020_s300.model
dynamixel_easy_sdk/control_table/ph54_100_s500.model
dynamixel_easy_sdk/control_table/ph54_200_s500.model
dynamixel_easy_sdk/control_table/pm42_010_s260.model
dynamixel_easy_sdk/control_table/pm54_040_s250.model
dynamixel_easy_sdk/control_table/pm54_060_s250.model
dynamixel_easy_sdk/control_table/rh_p12_rn.model
dynamixel_easy_sdk/control_table/xc330_m181.model
dynamixel_easy_sdk/control_table/xc330_m181_fw52.model
dynamixel_easy_sdk/control_table/xc330_m288.model
dynamixel_easy_sdk/control_table/xc330_m288_fw52.model
dynamixel_easy_sdk/control_table/xc330_t181.model
dynamixel_easy_sdk/control_table/xc330_t181_fw52.model
dynamixel_easy_sdk/control_table/xc330_t288.model
dynamixel_easy_sdk/control_table/xc330_t288_fw52.model
dynamixel_easy_sdk/control_table/xc430_w150.model
dynamixel_easy_sdk/control_table/xc430_w240.model
dynamixel_easy_sdk/control_table/xd430_t210.model
dynamixel_easy_sdk/control_table/xd430_t350.model
dynamixel_easy_sdk/control_table/xd540_t150.model
dynamixel_easy_sdk/control_table/xd540_t270.model
dynamixel_easy_sdk/control_table/xh430_v210.model
dynamixel_sdk-4.0.2.dist-info/licenses/LICENSE.txt
dynamixel_sdk-4.0.2.dist-info/METADATA
dynamixel_sdk-4.0.2.dist-info/WHEEL
dynamixel_sdk-4.0.2.dist-info/top_level.txt
dynamixel_sdk-4.0.2.dist-info/RECORD
