Metadata-Version: 2.4
Name: dynamixel-sdk
Version: 4.0.2
Summary: Dynamixel SDK 4. python package
Home-page: https://github.com/ROBOTIS-GIT/DynamixelSDK
Author: Leon Jung, Wonho Yun, Hyungyu Kim
Author-email: Leon Jung <rwjung@robotis.com>, Wonho Yun <ywh@robotis.com>, Hyungyu Kim <kimgf@robotis.com>
License: Apache 2.0
Project-URL: Homepage, https://github.com/ROBOTIS-GIT/DynamixelSDK
Requires-Python: >=3.6
License-File: LICENSE.txt
Requires-Dist: pyserial
Requires-Dist: importlib_resources; python_version < "3.9"
Dynamic: author
Dynamic: home-page
Dynamic: license-file
